bot_adapter/__init__.py
bot_adapter/apps.py
bot_adapter/bot.py
bot_adapter/urls.py
bot_adapter/views.py
django_python_telegram_bot_adapter-0.1.3.dist-info/LICENSE
django_python_telegram_bot_adapter-0.1.3.dist-info/METADATA
django_python_telegram_bot_adapter-0.1.3.dist-info/WHEEL
django_python_telegram_bot_adapter-0.1.3.dist-info/top_level.txt
django_python_telegram_bot_adapter-0.1.3.dist-info/RECORD
